{ "compressionlevel":-1,
 "editorsettings":
    {
     "export":
        {
         "format":"json",
         "target":"small.json"
        }
    },
 "height":10,
 "infinite":false,
 "layers":[
        {
         "data":[62, 63, 63, 63, 63, 63, 63, 63, 63, 64, 78, 79, 79, 79, 79, 79, 79, 79, 79, 80, 78, 79, 10, 11, 79, 79, 10, 11, 79, 80, 78, 79, 26, 27, 79, 79, 26, 27, 79, 80, 78, 79, 79, 79, 20, 21, 21, 22, 79, 80, 78, 79, 79, 79, 36, 58, 53, 54, 79, 80, 78, 79, 10, 11, 52, 54, 10, 11, 79, 80, 78, 79, 26, 27, 79, 79, 26, 27, 79, 80, 78, 101, 79, 79, 79, 79, 79, 79, 79, 80, 94, 95, 95, 95, 95, 95, 95, 95, 95, 96],
         "height":10,
         "id":1,
         "name":"Tile Layer 1",
         "opacity":1,
         "type":"tilelayer",
         "visible":true,
         "width":10,
         "x":0,
         "y":0
        }],
 "nextlayerid":2,
 "nextobjectid":1,
 "orientation":"orthogonal",
 "renderorder":"right-down",
 "tiledversion":"1.4.3",
 "tileheight":16,
 "tilesets":[
        {
         "firstgid":1,
         "source":"..\/..\/..\/..\/Users\/Jason\/Downloads\/art\/tiles\/first 8bit tileset.tsx"
        }],
 "tilewidth":16,
 "type":"map",
 "version":1.4,
 "width":10
}